{
	"info": {
		"_postman_id": "12d7a3ac-f76c-4775-8bd2-89acb97314b3",
		"name": "Program",
		"schema": "https://schema.getpostman.com/json/collection/v2.1.0/collection.json",
		"_exporter_id": "1830746"
	},
	"item": [
		{
			"name": "Palindrome",
			"request": {
				"method": "POST",
				"header": [],
				"body": {
					"mode": "raw",
					"raw": "{\r\n    \"check\": \"madam\"\r\n}",
					"options": {
						"raw": {
							"language": "json"
						}
					}
				},
				"url": {
					"raw": "http://localhost:3000/palindrome",
					"protocol": "http",
					"host": [
						"localhost"
					],
					"port": "3000",
					"path": [
						"palindrome"
					]
				}
			},
			"response": [
				{
					"name": "Palindrome",
					"originalRequest": {
						"method": "POST",
						"header": [],
						"body": {
							"mode": "raw",
							"raw": "{\r\n    \"check\": \"madam\"\r\n}",
							"options": {
								"raw": {
									"language": "json"
								}
							}
						},
						"url": {
							"raw": "http://localhost:3000/palindrome",
							"protocol": "http",
							"host": [
								"localhost"
							],
							"port": "3000",
							"path": [
								"palindrome"
							]
						}
					},
					"status": "OK",
					"code": 200,
					"_postman_previewlanguage": "json",
					"header": [
						{
							"key": "X-Powered-By",
							"value": "Express"
						},
						{
							"key": "Content-Type",
							"value": "application/json; charset=utf-8"
						},
						{
							"key": "Content-Length",
							"value": "25"
						},
						{
							"key": "ETag",
							"value": "W/\"19-LxUi7mB/s6+LdO023WQevXZ0xo8\""
						},
						{
							"key": "Date",
							"value": "Thu, 25 Aug 2022 09:10:27 GMT"
						},
						{
							"key": "Connection",
							"value": "keep-alive"
						},
						{
							"key": "Keep-Alive",
							"value": "timeout=5"
						}
					],
					"cookie": [],
					"body": "{\n    \"result\": \"A Palindrome\"\n}"
				}
			]
		},
		{
			"name": "FIzzBuzz",
			"request": {
				"method": "POST",
				"header": [],
				"body": {
					"mode": "raw",
					"raw": "{\r\n    \"check\": 100\r\n}",
					"options": {
						"raw": {
							"language": "json"
						}
					}
				},
				"url": {
					"raw": "http://localhost:3000/fizzbuzz",
					"protocol": "http",
					"host": [
						"localhost"
					],
					"port": "3000",
					"path": [
						"fizzbuzz"
					]
				}
			},
			"response": [
				{
					"name": "FIzzBuzz",
					"originalRequest": {
						"method": "POST",
						"header": [],
						"body": {
							"mode": "raw",
							"raw": "{\r\n    \"check\": 100\r\n}",
							"options": {
								"raw": {
									"language": "json"
								}
							}
						},
						"url": {
							"raw": "http://localhost:3000/fizzbuzz",
							"protocol": "http",
							"host": [
								"localhost"
							],
							"port": "3000",
							"path": [
								"fizzbuzz"
							]
						}
					},
					"status": "OK",
					"code": 200,
					"_postman_previewlanguage": "json",
					"header": [
						{
							"key": "X-Powered-By",
							"value": "Express"
						},
						{
							"key": "Content-Type",
							"value": "application/json; charset=utf-8"
						},
						{
							"key": "Content-Length",
							"value": "625"
						},
						{
							"key": "ETag",
							"value": "W/\"271-GI1+PXVIndh4UsYRzzWaIM0cszw\""
						},
						{
							"key": "Date",
							"value": "Thu, 25 Aug 2022 14:17:11 GMT"
						},
						{
							"key": "Connection",
							"value": "keep-alive"
						},
						{
							"key": "Keep-Alive",
							"value": "timeout=5"
						}
					],
					"cookie": [],
					"body": "{\n    \"result\": [\n        \"1\",\n        \"2\",\n        \"Fizz\",\n        \"4\",\n        \"Buzz\",\n        \"Fizz\",\n        \"7\",\n        \"8\",\n        \"Fizz\",\n        \"Buzz\",\n        \"11\",\n        \"Fizz\",\n        \"13\",\n        \"14\",\n        \"FizzBuzz\",\n        \"16\",\n        \"17\",\n        \"Fizz\",\n        \"19\",\n        \"Buzz\",\n        \"Fizz\",\n        \"22\",\n        \"23\",\n        \"Fizz\",\n        \"Buzz\",\n        \"26\",\n        \"Fizz\",\n        \"28\",\n        \"29\",\n        \"FizzBuzz\",\n        \"31\",\n        \"32\",\n        \"Fizz\",\n        \"34\",\n        \"Buzz\",\n        \"Fizz\",\n        \"37\",\n        \"38\",\n        \"Fizz\",\n        \"Buzz\",\n        \"41\",\n        \"Fizz\",\n        \"43\",\n        \"44\",\n        \"FizzBuzz\",\n        \"46\",\n        \"47\",\n        \"Fizz\",\n        \"49\",\n        \"Buzz\",\n        \"Fizz\",\n        \"52\",\n        \"53\",\n        \"Fizz\",\n        \"Buzz\",\n        \"56\",\n        \"Fizz\",\n        \"58\",\n        \"59\",\n        \"FizzBuzz\",\n        \"61\",\n        \"62\",\n        \"Fizz\",\n        \"64\",\n        \"Buzz\",\n        \"Fizz\",\n        \"67\",\n        \"68\",\n        \"Fizz\",\n        \"Buzz\",\n        \"71\",\n        \"Fizz\",\n        \"73\",\n        \"74\",\n        \"FizzBuzz\",\n        \"76\",\n        \"77\",\n        \"Fizz\",\n        \"79\",\n        \"Buzz\",\n        \"Fizz\",\n        \"82\",\n        \"83\",\n        \"Fizz\",\n        \"Buzz\",\n        \"86\",\n        \"Fizz\",\n        \"88\",\n        \"89\",\n        \"FizzBuzz\",\n        \"91\",\n        \"92\",\n        \"Fizz\",\n        \"94\",\n        \"Buzz\",\n        \"Fizz\",\n        \"97\",\n        \"98\",\n        \"Fizz\",\n        \"Buzz\"\n    ]\n}"
				}
			]
		}
	]
}